lackadaisical/VERSION
lackadaisical/__init__.py
lackadaisical/faster_than.py
lackadaisical/logging.py
lackadaisical/py.typed
lackadaisical/too_slow.py
lackadaisical-1.0.1.dist-info/LICENSE
lackadaisical-1.0.1.dist-info/METADATA
lackadaisical-1.0.1.dist-info/WHEEL
lackadaisical-1.0.1.dist-info/top_level.txt
lackadaisical-1.0.1.dist-info/RECORD
