Metadata-Version: 2.1
Name: lackadaisical
Version: 1.0.1
Summary: Keeps an eye on slow code
Author: Cariad Eccleston
Author-email: cariad@cariad.earth
License: MIT
Project-URL: Documentation, https://github.com/cariad/lackadaisical/blob/main/README.md
Project-URL: Source, https://github.com/cariad/lackadaisical
Classifier: Development Status :: 5 - Production/Stable
Classifier: License :: OSI Approved :: MIT License
Classifier: Natural Language :: English
Classifier: Operating System :: OS Independent
Classifier: Programming Language :: Python :: 3 :: Only
Classifier: Programming Language :: Python :: 3.10
Classifier: Programming Language :: Python :: 3.11
Classifier: Programming Language :: Python :: 3.9
Classifier: Typing :: Typed
Requires-Python: >=3.9
License-File: LICENSE
